n_queen_acog.py
n_queen_acog-0.1.0.dist-info/METADATA
n_queen_acog-0.1.0.dist-info/WHEEL
n_queen_acog-0.1.0.dist-info/RECORD
