Metadata-Version: 2.1
Name: n-queen-acog
Version: 0.1.0
Summary: A Python library for solving the N-Queens problem
Author: eknath
Author-email: eknath@aganitha.ai
Requires-Python: >=3.11,<4.0
Classifier: Programming Language :: Python :: 3
Classifier: Programming Language :: Python :: 3.11
Classifier: Programming Language :: Python :: 3.12
